maxvolpy/__init__.py
maxvolpy/__version__.py
maxvolpy/_maxvol.cpython-35m-darwin.so
maxvolpy/aux.py
maxvolpy/cross.py
maxvolpy/maxvol.py
maxvolpy/setup.py
maxvolpy-0.3.1.dist-info/DESCRIPTION.rst
maxvolpy-0.3.1.dist-info/METADATA
maxvolpy-0.3.1.dist-info/RECORD
maxvolpy-0.3.1.dist-info/WHEEL
maxvolpy-0.3.1.dist-info/metadata.json
maxvolpy-0.3.1.dist-info/top_level.txt
