Metadata-Version: 2.0
Name: maxvolpy
Version: 0.3.1
Summary: Cross and skeleton approximations, based on maximum volume submatrices.
Home-page: https://bitbucket.org/muxas/maxvolpy
Author: Alexander Mikhalev
Author-email: muxasizhevsk@gmail.com
License: MIT
Platform: UNKNOWN
Requires-Dist: cython (>=0.23.4)
Requires-Dist: numpy (>=1.10.1)
